Metadata-Version: 2.1
Name: aiocurl
Version: 0.0.1.post1
Summary: asyncio extension of PycURL
Home-page: https://github.com/fsbs/aiocurl
License: GNU AGPL v3
Project-URL: Bug Tracker, https://github.com/fsbs/aiocurl/issues
Keywords: asyncio,pycurl,async,libcurl,curl
Platform: any
Classifier: Development Status :: 2 - Pre-Alpha
Classifier: Programming Language :: Python :: 3
Classifier: Programming Language :: Python :: 3.7
Classifier: Programming Language :: Python :: 3.8
Classifier: Programming Language :: Python :: 3.9
Classifier: Programming Language :: Python :: 3.10
Classifier: License :: OSI Approved :: GNU Affero General Public License v3
Classifier: Operating System :: OS Independent
Requires-Python: >=3.7
License-File: COPYING
